odoo/addons/web_hide_field_with_key/README.rst
odoo/addons/web_hide_field_with_key/__init__.py
odoo/addons/web_hide_field_with_key/__manifest__.py
odoo/addons/web_hide_field_with_key/i18n/it.po
odoo/addons/web_hide_field_with_key/i18n/web_hide_field_with_key.pot
odoo/addons/web_hide_field_with_key/readme/CONTRIBUTORS.rst
odoo/addons/web_hide_field_with_key/readme/DESCRIPTION.rst
odoo/addons/web_hide_field_with_key/readme/USAGE.rst
odoo/addons/web_hide_field_with_key/static/description/icon.png
odoo/addons/web_hide_field_with_key/static/description/index.html
odoo/addons/web_hide_field_with_key/static/src/js/hide_custom_hidden_fields.js
odoo_addon_web_hide_field_with_key-16.0.1.0.1.1.dist-info/METADATA
odoo_addon_web_hide_field_with_key-16.0.1.0.1.1.dist-info/WHEEL
odoo_addon_web_hide_field_with_key-16.0.1.0.1.1.dist-info/top_level.txt
odoo_addon_web_hide_field_with_key-16.0.1.0.1.1.dist-info/RECORD
